openstock/__init__.py
openstock/stock/__init__.py
openstock/stock/client.py
openstock-0.0.8.dist-info/LICENSE
openstock-0.0.8.dist-info/METADATA
openstock-0.0.8.dist-info/WHEEL
openstock-0.0.8.dist-info/top_level.txt
openstock-0.0.8.dist-info/RECORD
