Metadata-Version: 2.1
Name: openstock
Version: 0.0.8
Summary: 一个股票行情工具包，可以用来获取股票历史k线数据
Home-page: https://github.com/geeeeeeeek/openstock
Author: Tim
Author-email: kefu308@gmail.com
License: UNKNOWN
Platform: UNKNOWN
Classifier: Programming Language :: Python :: 3
Classifier: License :: OSI Approved :: MIT License
Classifier: Operating System :: OS Independent
Requires-Python: >=3.8
Requires-Dist: akshare>=1.17.36
